klaatu_django/__init__.py
klaatu_django/actions.py
klaatu_django/admin.py
klaatu_django/apps.py
klaatu_django/authentication.py
klaatu_django/db.py
klaatu_django/forms.py
klaatu_django/managers.py
klaatu_django/permissions.py
klaatu_django/renderers.py
klaatu_django/routers.py
klaatu_django/schemas.py
klaatu_django/serializer_fields.py
klaatu_django/serializer_mixins.py
klaatu_django/settings.py
klaatu_django/storage.py
klaatu_django/test.py
klaatu_django/typing.py
klaatu_django/utils.py
klaatu_django/views.py
klaatu_django/widgets.py
klaatu_django/management/__init__.py
klaatu_django/management/base.py
klaatu_django/management/commands/__init__.py
klaatu_django/management/commands/classhierarchy.py
klaatu_django/management/commands/collectstatic.py
klaatu_django/management/commands/runserver.py
klaatu_django/migrations/__init__.py
klaatu_django/templates/admin/edit_inline/tabular_manytomany.html
klaatu_django/templates/klaatu/preloader.html
klaatu_django/templates/klaatu/modals/base.html
klaatu_django/templates/klaatu/modals/dynamic.html
klaatu_django/templates/klaatu/modals/dynamic_content.html
klaatu_django/templates/klaatu/widgets/custom_checkbox_select.html
klaatu_django/templatetags/__init__.py
klaatu_django/templatetags/klaatu.py
klaatu_django-4.1.0.dist-info/licenses/LICENSE
klaatu_django-4.1.0.dist-info/METADATA
klaatu_django-4.1.0.dist-info/WHEEL
klaatu_django-4.1.0.dist-info/top_level.txt
klaatu_django-4.1.0.dist-info/RECORD
