Metadata-Version: 2.4
Name: klaatu-django
Version: 4.1.0
Author-email: Robert Huselius <robert@huseli.us>
License-Expression: GPL-3.0-only
Project-URL: Homepage, https://github.com/Eboreg/klaatu-django
Project-URL: Source, https://github.com/Eboreg/klaatu-django
Project-URL: Issues, https://github.com/Eboreg/klaatu-django/issues
Requires-Python: >=3.10
License-File: LICENSE
Requires-Dist: beautifulsoup4
Requires-Dist: Django>=3.2
Requires-Dist: djangorestframework
Requires-Dist: klaatu-python
Requires-Dist: Pillow
Requires-Dist: python-dateutil
Provides-Extra: dev
Requires-Dist: flake8; extra == "dev"
Requires-Dist: ipdb; extra == "dev"
Requires-Dist: ipython; extra == "dev"
Requires-Dist: isort; extra == "dev"
Requires-Dist: mypy>=0.910; extra == "dev"
Requires-Dist: pylint; extra == "dev"
Requires-Dist: pylint-django; extra == "dev"
Requires-Dist: types-python-dateutil; extra == "dev"
Dynamic: license-file
